opsbox/__init__.py
opsbox/base_hooks.py
opsbox/cli.py
opsbox/config.py
opsbox/main.py
opsbox/plugins.py
opsbox/utils.py
opsbox-0.2.5.dist-info/licenses/LICENCE.txt
opsbox-0.2.5.dist-info/METADATA
opsbox-0.2.5.dist-info/WHEEL
opsbox-0.2.5.dist-info/entry_points.txt
opsbox-0.2.5.dist-info/top_level.txt
opsbox-0.2.5.dist-info/RECORD
