Metadata-Version: 2.4
Name: opsbox
Version: 0.2.5
Summary: AI-powered infrastructure management
Author-email: Opsbox Team <opsbox@gsudoers.com>
License: Mozilla Public License Version 2.0
Project-URL: Documentation, https://sudoersllc.github.io/opsbox-docs/core/
Project-URL: Repository, https://github.com/sudoersllc/opsbox-core.git
Project-URL: Issues, https://github.com/sudoersllc/opsbox-core/issues
Classifier: Environment :: Console
Classifier: Programming Language :: Python :: 3
Classifier: Intended Audience :: Developers
Classifier: Topic :: System :: Systems Administration
Classifier: Topic :: Utilities
Classifier: License :: OSI Approved :: Mozilla Public License 2.0 (MPL 2.0)
Requires-Python: ==3.11.*
License-File: LICENCE.txt
Requires-Dist: pluggy<2.0.0,>=1.5.0
Requires-Dist: loguru<0.8.0,>=0.7.2
Requires-Dist: pydantic<3.0.0,>=2.8.0
Requires-Dist: rich-argparse<2.0.0,>=1.5.2
Requires-Dist: requests<3.0.0,>=2.32.3
Requires-Dist: python-dotenv<2.0.0,>=1.0.1
Requires-Dist: llama-index<0.13.0,>=0.12.0
Requires-Dist: toml<0.11.0,>=0.10.2
Requires-Dist: importlib-resources>=6.4.5
Requires-Dist: llama-index-llms-anthropic>=0.6.3
Requires-Dist: dateparser>=1.2.0
Requires-Dist: markdown>=3.7
Provides-Extra: aws
Requires-Dist: opsbox-s3-checks>=0.2.0; extra == "aws"
Requires-Dist: opsbox-ec2-checks>=0.2.0; extra == "aws"
Requires-Dist: opsbox-elb-checks>=0.2.0; extra == "aws"
Requires-Dist: opsbox-aws-iam-checks>=0.2.0; extra == "aws"
Requires-Dist: opsbox-r53-checks>=0.2.0; extra == "aws"
Requires-Dist: opsbox-rds-checks>=0.2.0; extra == "aws"
Requires-Dist: opsbox-general-handler>=0.2.0; extra == "aws"
Requires-Dist: opsbox-rego-handler>=0.2.1; extra == "aws"
Dynamic: license-file
